{
  "itemCount": 1,
  "products": [
    {
      "@odata.etag": "W/\"JzE5OzQxNTM4Mzg0OTA4MzIxMDE0ODUxOzAwOyc=\"",
      "No": "ISODISTRANSP",
      "Description": "FRAIS DE TRANSPORT ISODIS",
      "Description_2": "",
      "Type": "Inventory",
      "InventoryField": 24,
      "Inventory_Disponibility": 0,
      "Created_From_Nonstock_Item": false,
      "Substitutes_Exist": false,
      "Stockkeeping_Unit_Exists": false,
      "Assembly_BOM": false,
      "Production_BOM_No": "",
      "Routing_No": "",
      "Base_Unit_of_Measure": "PCS",
      "Shelf_No": "",
      "Costing_Method": "Average",
      "Cost_is_Adjusted": true,
      "Standard_Cost": 0,
      "Unit_Cost": 245.02333,
      "Last_Direct_Cost": 252.71429,
      "Price_Profit_Calculation": "Profit=Price-Cost",
      "Profit_Percent": 0,
      "Unit_Price": 0,
      "Inventory_Posting_Group": "NEGOCE",
      "Gen_Prod_Posting_Group": "MARCHANDISES",
      "VAT_Prod_Posting_Group": "TND",
      "Item_Disc_Group": "",
      "Vendor_No": "",
      "Vendor_Item_No": "",
      "Tariff_No": "",
      "Search_Description": "FRAIS DE TRANSPORT ISODIS",
      "Overhead_Rate": 0,
      "Indirect_Cost_Percent": 0,
      "Item_Category_Code": "TRANSPORT",
      "Parent_Category": "",
      "Blocked": false,
      "Last_Date_Modified": "2023-01-19",
      "Sales_Unit_of_Measure": "PCS",
      "Replenishment_System": "Purchase",
      "Purch_Unit_of_Measure": "PCS",
      "Lead_Time_Calculation": "",
      "Manufacturing_Policy": "Make-to-Stock",
      "Flushing_Method": "Manual",
      "Assembly_Policy": "Assemble-to-Stock",
      "Item_Tracking_Code": "",
      "Default_Deferral_Template_Code": "",
      "Coupled_to_CRM": false,
      "Coupled_to_Dataverse": false,
      "GTIN": "",
      "SystemCreatedAt": "2022-02-03T14:15:41.45Z",
      "Global_Dimension_1_Filter": "",
      "Global_Dimension_2_Filter": "",
      "Location_Filter": "",
      "Drop_Shipment_Filter": "",
      "Variant_Filter": "",
      "Lot_No_Filter": "",
      "Serial_No_Filter": "",
      "Unit_of_Measure_Filter": "",
      "Package_No_Filter": ""
    }
  ]
}